Delay.v
`timescale 1ns / 1ps

module Delay(
    input CLK,
    input RST,
    input [11:0] DELAY_MS,
    input DELAY_EN,
    output DELAY_FIN
);
    reg [31:0] current_state = "Idle";       // Signal for state machine
    reg [16:0] clk_counter = 17'b00000000000000000;  // Counts up on every rising edge of CLK
    reg [11:0] ms_counter = 12'h000;       // Counts up when clk_counter = 100,000

    assign DELAY_FIN = (current_state == "Done" && DELAY_EN == 1'b1) ? 1'b1 : 1'b0;

    //  State Machine
    always @(posedge CLK) begin
        // When RST is asserted switch to idle (synchronous)
        if(RST == 1'b1) begin
            current_state <= "Idle";
        end else begin
            case(current_state)
                "Idle" : begin
                    // Start delay on DELAY_EN
                    if(DELAY_EN == 1'b1) begin
                        current_state <= "Hold";
                    end
                end
                "Hold" : begin
                    // Stay until DELAY_MS has occured
                    if(ms_counter == DELAY_MS) begin
                        current_state <= "Done";
                    end
                end
                "Done" : begin
                    // Wait until DELAY_EN is deasserted to go to IDLE
                    if(DELAY_EN == 1'b0) begin
                        current_state <= "Idle";
                    end
                end
                default : current_state <= "Idle";
            endcase
        end
    end

    //  Clock Divider
    always @(posedge CLK) begin
        if(current_state == "Hold") begin
            if(clk_counter == 17'b11000011010100000) begin   // 100,000
                clk_counter <= 17'b00000000000000000;
                ms_counter <= ms_counter + 1'b1;       // increments at 1KHz
            end else begin
                clk_counter <= clk_counter + 1'b1;
            end
        end else begin
            // If not in the hold state reset counters
            clk_counter <= 17'b00000000000000000;
            ms_counter <= 12'h000;
        end
    end
endmodule

SpiControl.v
`timescale 1ns / 1ps

module SpiControl(
    CLK,
    RST,
    SPI_EN,
    SPI_DATA,
    CS,
    SDO,
    SCLK,
    SPI_FIN
    );

    input CLK;
    input RST;
    input SPI_EN;
    input [7:0] SPI_DATA;
    output CS;
    output SDO;
    output SCLK;
    output SPI_FIN;


	wire CS, SDO, SCLK, SPI_FIN;

	reg [39:0] current_state = "Idle";		// Signal for state machine
	
	reg [7:0] shift_register = 8'h00;		// Shift register to shift out SPI_DATA saved when SPI_EN was set
	reg [3:0] shift_counter = 4'h0;			// Keeps track how many bits were sent
	wire clk_divided;						// Used as SCLK
	reg [4:0] counter = 5'b00000;				// Count clocks to be used to divide CLK
	reg temp_sdo = 1'b1;							// Tied to SDO
	
	reg falling = 1'b0;							// signal indicating that the clk has just fell

	assign clk_divided = ~counter[4];
	assign SCLK = clk_divided;
	assign SDO = temp_sdo;
	
	assign CS = (current_state == "Idle" && SPI_EN == 1'b0) ? 1'b1 : 1'b0;
	assign SPI_FIN = (current_state == "Done") ? 1'b1 : 1'b0;
	
	//  State Machine
	always @(posedge CLK) begin
			if(RST == 1'b1) begin							// Synchronous RST
				current_state <= "Idle";
			end
			else begin
			
				case(current_state)

					// Wait for SPI_EN to go high
					"Idle" : begin
						if(SPI_EN == 1'b1) begin
							current_state <= "Send";
						end
					end

					// Start sending bits, transition out when all bits are sent and SCLK is high
					"Send" : begin
						if(shift_counter == 4'h8 && falling == 1'b0) begin
							current_state <= "Hold1";
						end
					end
					
					// Hold CS low for a bit
					"Hold1" : begin
						current_state <= "Hold2";
					end

					// Hold CS low for a bit
					"Hold2" : begin
						current_state <= "Hold3";
					end

					// Hold CS low for a bit
					"Hold3" : begin
						current_state <= "Hold4";
					end

					// Hold CS low for a bit
					"Hold4" : begin
						current_state <= "Done";
					end

					// Finish SPI transimission wait for SPI_EN to go low
					"Done" : begin
						if(SPI_EN == 1'b0) begin
							current_state <= "Idle";
						end
					end

					default : current_state <= "Idle";

				endcase
			end
	end
	//  End of State Machine

	
	//  Clock Divider
	always @(posedge CLK) begin
			//  start clock counter when in send state
			if(current_state == "Send") begin
				counter <= counter + 1'b1;
			end
			//  reset clock counter when not in send state
			else begin
				counter <= 5'b00000;
			end
	end
	//  End Clock Divider
	
	
	//  SPI_SEND_BYTE,  sends SPI data formatted SCLK active low with SDO changing on the falling edge
	always @(posedge CLK) begin
			if(current_state == "Idle") begin
					shift_counter <= 4'h0;
					// keeps placing SPI_DATA into shift_register so that when state goes to send it has the latest SPI_DATA
					shift_register <= SPI_DATA;
					temp_sdo <= 1'b1;
			end
			else if(current_state == "Send") begin
					//  if on the falling edge of Clk_divided
					if(clk_divided == 1'b0 && falling == 1'b0) begin
							//  Indicate that it is passed the falling edge
							falling <= 1'b1;
							// send out the MSB
							temp_sdo <= shift_register[7];
							//  Shift through SPI_DATA
							shift_register <= {shift_register[6:0],1'b0};
							//  Keep track of what bit it is on
							shift_counter <= shift_counter + 1'b1;
					end
					//  on SCLK high reset the falling flag
					else if(clk_divided == 1'b1) begin
						falling <= 1'b0;
					end
			end
	end

endmodule

OledInit.v
`timescale 1ns / 1ps

module OledInit(
    CLK,
    EN,
    RST,
    CS,
    DC,
    FIN,
    RES,
    SCLK,
    SDO,
    VBAT,
    VDD
    );

	// ===========================================================================
	// 										Port Declarations
	// ===========================================================================
    input CLK;
    input EN;
    input RST;
    output CS;
    output DC;
    output FIN;
    output RES;
    output SCLK;
    output SDO;
    output VBAT;
    output VDD;

	// ===========================================================================
	// 							  Parameters, Regsiters, and Wires
	// ===========================================================================
	wire DC, RES, VBAT, VDD, FIN;
	wire CS, SCLK, SDO;

	reg [103:0] current_state = "Idle";
	reg [103:0] after_state = "Idle";

	reg temp_dc = 1'b0;
	reg temp_res = 1'b1;
	reg temp_vbat = 1'b1;
	reg temp_vdd = 1'b1;
	reg temp_fin = 1'b0;
	
	wire [11:0] temp_delay_ms;
	reg temp_delay_en = 1'b0;
	wire temp_delay_fin;
	reg temp_spi_en = 1'b0;
	reg [7:0] temp_spi_data = 8'h00;
	wire temp_spi_fin;

	// ===========================================================================
	// 										Implementation
	// ===========================================================================	
	SpiControl SPI_COMP(
			.CLK(CLK),
			.RST(RST),
			.SPI_EN(temp_spi_en),
			.SPI_DATA(temp_spi_data),
			.CS(CS),
			.SDO(SDO),
			.SCLK(SCLK),
			.SPI_FIN(temp_spi_fin)
	);
	
	Delay DELAY_COMP(
			.CLK(CLK),
			.RST(RST),
			.DELAY_MS(temp_delay_ms),
			.DELAY_EN(temp_delay_en),
			.DELAY_FIN(temp_delay_fin)
	);

	assign DC = temp_dc;
	assign RES = temp_res;
	assign VBAT = temp_vbat;
	assign VDD = temp_vdd;
	assign FIN = temp_fin;

	// Delay 100 ms after VbatOn
	assign temp_delay_ms = (after_state == "DispContrast1") ? 12'h064 : 12'h001;


	// State Machine
	always @(posedge CLK) begin
			if(RST == 1'b1) begin
					current_state <= "Idle";
					temp_res <= 1'b0;
			end
			else begin
					temp_res <= 1'b1;
					
					case(current_state)

							// Idle State
							"Idle" : begin
									if(EN == 1'b1) begin
										temp_dc <= 1'b0;
										current_state <= "VddOn";
									end
							end

							// Initialization Sequence
							// This should be done everytime the PmodOLED is started
							"VddOn" : begin
								temp_vdd <= 1'b0;
								current_state <= "Wait1";
							end

							// 3
							"Wait1" : begin
								after_state <= "DispOff";
								current_state <= "Transition3";
							end

							// 4
							"DispOff" : begin
								temp_spi_data <= 8'hAE; // 0xAE
								after_state <= "ResetOn";
								current_state <= "Transition1";
							end

							// 5
							"ResetOn" : begin
								temp_res <= 1'b0;
								current_state <= "Wait2";
							end

							// 6							
							"Wait2" : begin
								after_state <= "ResetOff";
								current_state <= "Transition3";
							end

							// 7
							"ResetOff" : begin
								temp_res <= 1'b1;
								after_state <= "ChargePump1";
								current_state <= "Transition3";
							end

							// 8
							"ChargePump1" : begin
								temp_spi_data <= 8'h8D; //0x8D
								after_state <= "ChargePump2";
								current_state <= "Transition1";
							end

							// 9
							"ChargePump2" : begin
								temp_spi_data <= 8'h14; // 0x14
								after_state <= "PreCharge1";
								current_state <= "Transition1";
							end

							// 10
							"PreCharge1" : begin
								temp_spi_data <= 8'hD9; // 0xD9
								after_state <= "PreCharge2";
								current_state <= "Transition1";
							end

							// 11
							"PreCharge2" : begin
								temp_spi_data <= 8'hF1; // 0xF1
								after_state <= "VbatOn";
								current_state <= "Transition1";
							end

							// 12
							"VbatOn" : begin
								temp_vbat <= 1'b0;
								current_state <= "Wait3";
							end

							// 13
							"Wait3" : begin
								after_state <= "DispContrast1";
								current_state <= "Transition3";
							end

							// 14
							"DispContrast1" : begin
								temp_spi_data <= 8'h81; // 0x81
								after_state <= "DispContrast2";
								current_state <= "Transition1";
							end

							// 15
							"DispContrast2" : begin
								temp_spi_data <= 8'h0F; // 0x0F
								after_state <= "InvertDisp1";
								current_state <= "Transition1";
							end

							// 16
							"InvertDisp1" : begin
								temp_spi_data <= 8'hA1; // 0xA1
								after_state <= "InvertDisp2";
								current_state <= "Transition1";
							end

							// 17
							"InvertDisp2" : begin
								temp_spi_data <= 8'hC8; // 0xC8
								after_state <= "ComConfig1";
								current_state <= "Transition1";
							end

							// 18
							"ComConfig1" : begin
								temp_spi_data <= 8'hDA; // 0xDA
								after_state <= "ComConfig2";
								current_state <= "Transition1";
							end

							// 19
							"ComConfig2" : begin
								temp_spi_data <= 8'h20; // 0x20
								after_state <= "DispOn";
								current_state <= "Transition1";
							end

							// 20
							"DispOn" : begin
								temp_spi_data <= 8'hAF; // 0xAF
								after_state <= "Done";
								current_state <= "Transition1";
							end
						   // ************ END Initialization sequence ************

							// Used for debugging, This command turns the entire screen on regardless of memory
							"FullDisp" : begin
								temp_spi_data <= 8'hA5; // 0xA5
								after_state <= "Done";
								current_state <= "Transition1";
							end

						   // Done state
							"Done" : begin
								if(EN == 1'b0) begin
									temp_fin <= 1'b0;
									current_state <= "Idle";
								end
								else begin
									temp_fin <= 1'b1;
								end
							end

							// SPI transitions
							// 1. Set SPI_EN to 1
							// 2. Waits for SpiCtrl to finish
							// 3. Goes to clear state (Transition5)
							"Transition1" : begin
								temp_spi_en <= 1'b1;
								current_state <= "Transition2";
							end

							// 24
							"Transition2" : begin
								if(temp_spi_fin == 1'b1) begin
									current_state <= "Transition5";
								end
							end

							// Delay Transitions
							// 1. Set DELAY_EN to 1
							// 2. Waits for Delay to finish
							// 3. Goes to Clear state (Transition5)	
							"Transition3" : begin
								temp_delay_en <= 1'b1;
								current_state <= "Transition4";
							end

							// 26
							"Transition4" : begin
								if(temp_delay_fin == 1'b1) begin
									current_state <= "Transition5";
								end
							end

							// Clear transition
							// 1. Sets both DELAY_EN and SPI_EN to 0
							// 2. Go to after state
							"Transition5" : begin
								temp_spi_en <= 1'b0;
								temp_delay_en <= 1'b0;
								current_state <= after_state;
							end

							default : current_state <= "Idle";

					endcase
			end
	end

endmodule

SpiMaster.v
`timescale 1ns / 1ps

module SpiMaster(
    input clk,
    input reset,
    input start,
    input [7:0] data,
    output reg done,
    output reg mosi,
    output reg sck,
    output reg cs
);
    reg [2:0] bit_cnt;
    reg [7:0] shift_reg;
    reg [1:0] state;
    reg [4:0] clk_div;

    parameter IDLE = 2'b00;
    parameter SEND = 2'b01;
    parameter DONE = 2'b10;

    initial begin
        state <= IDLE;
        cs <= 1;
        sck <= 0;
        mosi <= 0;
        done <= 0;
        bit_cnt <= 0;
        shift_reg <= 8'b0;
        clk_div <= 0;
    end

    always @(posedge clk or posedge reset) begin
        if (reset) begin
            state <= IDLE;
            cs <= 1;
            sck <= 0;
            mosi <= 0;
            done <= 0;
            bit_cnt <= 0;
            shift_reg <= 8'b0;
            clk_div <= 0;
        end else begin
            case (state)
                IDLE: begin
                    cs <= 1;
                    sck <= 0;
                    done <= 0;
                    if (start) begin
                        shift_reg <= data;
                        bit_cnt <= 7;
                        cs <= 0;
                        state <= SEND;
                    end
                end
                SEND: begin
                    clk_div <= clk_div + 1;
                    if (clk_div == 5'b11111) begin
                        clk_div <= 0;
                        sck <= ~sck;
                        if (~sck) begin
                            mosi <= shift_reg[bit_cnt];
                            bit_cnt <= bit_cnt - 1;
                            if (bit_cnt == 0) begin
                                state <= DONE;
                            end
                        end
                    end
                end
                DONE: begin
                    cs <= 1;
                    done <= 1;
                    state <= IDLE;
                end
            endcase
        end
    end
endmodule

Random/Random.v
module Random (
    input clk,
    input rst,
    output reg [6:0] randX,
    output reg [6:0] randY
);
    reg [6:0] lfsrX = 7'b1010101; // Initial seed for randX
    reg [6:0] lfsrY = 7'b0110110;  // Initial seed for randY

    always @(posedge clk) begin
        if (rst) 
            begin
                lfsrX <= 7'b1010101; // Reset
                lfsrY <= 7'b0110110; // Reset 
            end 
        else 
            begin
                // LFSR for randX (7-bit)
                lfsrX <= {lfsrX[5:0], lfsrX[6] ^ lfsrX[5]};  
                randX <= lfsrX;

                // LFSR for randY (7-bit)
                lfsrY <= {lfsrY[5:0], lfsrY[6] ^ lfsrY[5]};  
                randY <= lfsrY;
            end
    end
endmodule

ButtonInput.v
module ButtonInput (
    input wire clk,
    input wire l,  // Left
    input wire r,  // Right
    input wire u,  // Up
    input wire d,  // Down
    output reg [3:0] direction
);
    localparam LEFT  = 4'b0001;
    localparam RIGHT = 4'b0010;
    localparam UP    = 4'b0100;
    localparam DOWN  = 4'b1000;

    always @(posedge clk) begin
        if (l)
            direction <= LEFT;
        else if (r)
            direction <= RIGHT;
        else if (u)
            direction <= UP;
        else if (d)
            direction <= DOWN;
        // No change for no input or simultaneous button presses
    end
endmodule

Snake.v
`timescale 1ns / 1ps

module Snake(
    input clk,
    input reset,
    input l,
    input r,  
    input u,  
    input d, 
    output mosi,
    output sck,
    output cs,
    output dc,
    output vbat,
    output vdd,
    output res
);
    wire [3:0] direction;
    ButtonInput but(clk, l, r, u, d, direction);

    wire [6:0] randX, randY;
    Random ran(clk, reset, randX, randY);

    reg [7:0] spi_data;
    reg spi_start = 0;
    wire spi_done;
    SpiMaster spi0(clk, reset, spi_start, spi_data, spi_done, mosi, sck, cs);

    // OLED initialization and control
    reg oled_init_start = 0;
    wire oled_init_done;
    OledInit oled_init(
        .CLK(clk),
        .EN(oled_init_start),
        .RST(reset),
        .CS(cs),
        .DC(dc),
        .FIN(oled_init_done),
        .RES(res),
        .SCLK(sck),
        .SDO(mosi),
        .VBAT(vbat),
        .VDD(vdd)
    );

    // Adjusted for a 96x64 OLED display
    reg [767:0] display_buffer;  // Each bit represents a pixel (96x64 / 8 = 768 bytes)
    reg [9:0] buffer_addr = 0;

    // Snake and apple properties
    reg [6:0] snake_x = 20, snake_y = 20;  // Initial snake position
    reg [6:0] apple_x = 48, apple_y = 32;  // Initial apple position
    reg game_over = 0;

    localparam LEFT  = 4'b0001;
    localparam RIGHT = 4'b0010;
    localparam UP    = 4'b0100;
    localparam DOWN  = 4'b1000;

    // Update the display buffer and send to the OLED via SPI
    always @(posedge clk) begin
        if (reset) begin
            // Reset logic
            buffer_addr <= 0;
            spi_start <= 0;
            oled_init_start <= 1;
            snake_x <= 20;
            snake_y <= 20;
            apple_x <= 48;
            apple_y <= 32;
            game_over <= 0;
            display_buffer <= 0;
        end else if (oled_init_done) begin
            oled_init_start <= 0;
            if (spi_done && buffer_addr < 768) begin
                spi_start <= 1;
                spi_data <= display_buffer[buffer_addr * 8 +: 8];
                buffer_addr <= buffer_addr + 1;
            end else if (buffer_addr >= 768) begin
                buffer_addr <= 0;  // Restart buffer cycle
            end
        end
    end

    // Game logic to update display_buffer based on game state
    integer i;
    always @(posedge clk) begin
        if (!reset && !game_over) begin
            // Clear display buffer each frame
            for (i = 0; i < 768; i = i + 1) begin
                display_buffer[i] <= 0;
            end

            // Update apple position in display buffer
            display_buffer[apple_x + apple_y * 96] <= 1;

            // Update snake position in display buffer
            display_buffer[snake_x + snake_y * 96] <= 1;

            // Handle direction input and move snake
            case (direction)
                LEFT: snake_x <= (snake_x > 0) ? snake_x - 1 : 63;  // Left
                RIGHT: snake_x <= (snake_x < 63) ? snake_x + 1 : 0;  // Right
                UP: snake_y <= (snake_y > 0) ? snake_y + 1 : 95;  // Up
                DOWN: snake_y <= (snake_y < 95) ? snake_y - 1 : 0;  // Down
            endcase

            // Check for collisions with boundaries or apple
            if (snake_x == 0 || snake_x == 96 || snake_y == 0 || snake_y == 64) begin
                game_over <= 1;
            end else if (snake_x == apple_x && snake_y == apple_y) begin
                // Randomly reposition the apple
                apple_x <= randX;  
                apple_y <= randY;  
            end
        end
    end
endmodule

Snake_tb.v
`timescale 1ns / 1ps

module Snake_tb;
    // Inputs
    reg clk;
    reg reset;
    reg l;
    reg r;
    reg u;
    reg d;

    // Outputs
    wire mosi;
    wire sck;
    wire cs;
    wire dc;
    wire vbat;
    wire vdd;
    wire res;

    // Instantiate the Unit Under Test (UUT)
    Snake uut (
        .clk(clk),
        .reset(reset),
        .l(l),
        .r(r),
        .u(u),
        .d(d),
        .mosi(mosi),
        .sck(sck),
        .cs(cs),
        .dc(dc),
        .vbat(vbat),
        .vdd(vdd),
        .res(res)
    );

    // Clock generation
    always #5 clk = ~clk; // 100 MHz clock

    initial begin
        // Initialize Inputs
        clk = 0;
        reset = 1;
        l = 0;
        r = 0;
        u = 0;
        d = 0;

        // Wait 100 ns for global reset to finish
        #100;
        
        // Release reset
        reset = 0;
        
        // Wait for OLED initialization to complete
        #100000; // Adjust based on OLED initialization time
        
        // Test movement
        // Move right
        r = 1; #20; r = 0; #80;
        
        // Move down
        d = 1; #20; d = 0; #80;
        
        // Move left
        l = 1; #20; l = 0; #80;
        
        // Move up
        u = 1; #20; u = 0; #80;
        
        // Test reset
        reset = 1; #20; reset = 0;
        
        // End of simulation
        #1000;
        $stop;
    end

    initial begin
        $dumpfile("snake_game_tb.vcd");
        $dumpvars(0, Snake_tb);
    end

    // Monitor statements
    initial begin
        $monitor("Time = %0t | reset = %b | l = %b | r = %b | u = %b | d = %b | snake_x = %d | snake_y = %d | apple_x = %d | apple_y = %d | game_over = %b",
            $time, reset, l, r, u, d, uut.snake_x, uut.snake_y, uut.apple_x, uut.apple_y, uut.game_over);
    end
endmodule

snake_game_tb.vcd
$date
	Thu Jun 20 12:18:00 2024
$end
$version
	Icarus Verilog
$end
$timescale
	1ps
$end
$scope module Snake_tb $end
$var wire 1 ! cs $end
$var wire 1 " mosi $end
$var wire 1 # sck $end
$var wire 1 $ vdd $end
$var wire 1 % vbat $end
$var wire 1 & res $end
$var wire 1 ' dc $end
$var reg 1 ( clk $end
$var reg 1 ) d $end
$var reg 1 * l $end
$var reg 1 + r $end
$var reg 1 , reset $end
$var reg 1 - u $end
$scope module uut $end
$var wire 1 ( clk $end
$var wire 1 ! cs $end
$var wire 1 ) d $end
$var wire 1 * l $end
$var wire 1 " mosi $end
$var wire 1 + r $end
$var wire 1 , reset $end
$var wire 1 # sck $end
$var wire 1 - u $end
$var wire 1 $ vdd $end
$var wire 1 % vbat $end
$var wire 1 . spi_done $end
$var wire 1 & res $end
$var wire 7 / randY [6:0] $end
$var wire 7 0 randX [6:0] $end
$var wire 1 1 oled_init_done $end
$var wire 4 2 direction [3:0] $end
$var wire 1 ' dc $end
$var parameter 4 3 DOWN $end
$var parameter 4 4 LEFT $end
$var parameter 4 5 RIGHT $end
$var parameter 4 6 UP $end
$var reg 7 7 apple_x [6:0] $end
$var reg 7 8 apple_y [6:0] $end
$var reg 10 9 buffer_addr [9:0] $end
$var reg 768 : display_buffer [767:0] $end
$var reg 1 ; game_over $end
$var reg 1 < oled_init_start $end
$var reg 7 = snake_x [6:0] $end
$var reg 7 > snake_y [6:0] $end
$var reg 8 ? spi_data [7:0] $end
$var reg 1 @ spi_start $end
$var integer 32 A i [31:0] $end
$scope module but $end
$var wire 1 ( clk $end
$var wire 1 ) d $end
$var wire 1 * l $end
$var wire 1 + r $end
$var wire 1 - u $end
$var parameter 4 B DOWN $end
$var parameter 4 C LEFT $end
$var parameter 4 D RIGHT $end
$var parameter 4 E UP $end
$var reg 4 F direction [3:0] $end
$upscope $end
$scope module oled_init $end
$var wire 1 ( CLK $end
$var wire 1 ! CS $end
$var wire 1 ' DC $end
$var wire 1 < EN $end
$var wire 1 1 FIN $end
$var wire 1 & RES $end
$var wire 1 , RST $end
$var wire 1 # SCLK $end
$var wire 1 " SDO $end
$var wire 1 % VBAT $end
$var wire 1 $ VDD $end
$var wire 1 G temp_spi_fin $end
$var wire 12 H temp_delay_ms [11:0] $end
$var wire 1 I temp_delay_fin $end
$var reg 104 J after_state [103:0] $end
$var reg 104 K current_state [103:0] $end
$var reg 1 L temp_dc $end
$var reg 1 M temp_delay_en $end
$var reg 1 N temp_fin $end
$var reg 1 O temp_res $end
$var reg 8 P temp_spi_data [7:0] $end
$var reg 1 Q temp_spi_en $end
$var reg 1 R temp_vbat $end
$var reg 1 S temp_vdd $end
$scope module DELAY_COMP $end
$var wire 1 ( CLK $end
$var wire 1 M DELAY_EN $end
$var wire 12 T DELAY_MS [11:0] $end
$var wire 1 , RST $end
$var wire 1 I DELAY_FIN $end
$var reg 17 U clk_counter [16:0] $end
$var reg 32 V current_state [31:0] $end
$var reg 12 W ms_counter [11:0] $end
$upscope $end
$scope module SPI_COMP $end
$var wire 1 ( CLK $end
$var wire 1 ! CS $end
$var wire 1 , RST $end
$var wire 1 # SCLK $end
$var wire 1 " SDO $end
$var wire 8 X SPI_DATA [7:0] $end
$var wire 1 Q SPI_EN $end
$var wire 1 Y clk_divided $end
$var wire 1 G SPI_FIN $end
$var reg 5 Z counter [4:0] $end
$var reg 40 [ current_state [39:0] $end
$var reg 1 \ falling $end
$var reg 4 ] shift_counter [3:0] $end
$var reg 8 ^ shift_register [7:0] $end
$var reg 1 _ temp_sdo $end
$upscope $end
$upscope $end
$scope module ran $end
$var wire 1 ( clk $end
$var wire 1 , rst $end
$var reg 7 ` lfsrX [6:0] $end
$var reg 7 a lfsrY [6:0] $end
$var reg 7 b randX [6:0] $end
$var reg 7 c randY [6:0] $end
$upscope $end
$scope module spi0 $end
$var wire 1 ( clk $end
$var wire 8 d data [7:0] $end
$var wire 1 , reset $end
$var wire 1 @ start $end
$var parameter 2 e DONE $end
$var parameter 2 f IDLE $end
$var parameter 2 g SEND $end
$var reg 3 h bit_cnt [2:0] $end
$var reg 5 i clk_div [4:0] $end
$var reg 1 j cs $end
$var reg 1 . done $end
$var reg 1 k mosi $end
$var reg 1 l sck $end
$var reg 8 m shift_reg [7:0] $end
$var reg 2 n state [1:0] $end
$upscope $end
$upscope $end
$upscope $end
$enddefinitions $end
$comment Show the parameter values. $end
$dumpall
b1 g
b0 f
b10 e
b100 E
b10 D
b1 C
b1000 B
b100 6
b10 5
b1 4
b1000 3
$end
#0
$dumpvars
b0 n
b0 m
0l
0k
1j
b0 i
b0 h
bx d
bx c
bx b
b110110 a
b1010101 `
1_
b0 ^
b0 ]
0\
b1001001011001000110110001100101 [
b0 Z
1Y
b0 X
b0 W
b1001001011001000110110001100101 V
b0 U
b1 T
1S
1R
0Q
b0 P
1O
0N
0M
0L
b1001001011001000110110001100101 K
b1001001011001000110110001100101 J
0I
b1 H
0G
bx F
bx A
0@
bx ?
b10100 >
b10100 =
0<
0;
bx :
b0 9
b100000 8
b110000 7
bx 2
01
bx 0
bx /
0.
0-
1,
0+
0*
0)
0(
0'
1&
1%
1$
x#
x"
1!
$end
#5000
0&
0O
b0 :
1<
1(
#10000
0(
#15000
1(
#20000
0(
#25000
1(
#30000
0(
#35000
1(
#40000
0(
#45000
1(
#50000
0(
#55000
1(
#60000
0(
#65000
1(
#70000
0(
#75000
1(
#80000
0(
#85000
1(
#90000
0(
#95000
1(
#100000
0(
0,
#105000
b110110 /
b110110 c
b1101101 a
b1010101 0
b1010101 b
b101011 `
b101011001100100011001000100111101101110 K
1&
1O
b1100000000 A
1(
#110000
0(
#115000
b101011101100001011010010111010000110001 K
0$
0S
b1000000 /
b1000000 c
b1011010 a
b101011 0
b101011 b
b1010111 `
b1100000000 A
1(
#120000
0(
#125000
b110101 a
b1010111 0
b1010111 b
b101111 `
b101010001110010011000010110111001110011011010010111010001101001011011110110111000110011 K
b1000100011010010111001101110000010011110110011001100110 J
b1100000000 A
1(
#130000
0(
#135000
b101010001110010011000010110111001110011011010010111010001101001011011110110111000110100 K
1M
b110101 /
b110101 c
b1101011 a
b101111 0
b101111 b
b1011111 `
b1100000000 A
1(
#140000
0(
#145000
b1000000 /
b1000000 c
b1010110 a
b1011111 0
b1011111 b
b111111 `
b1001000011011110110110001100100 V
b1100000000 A
1(
#150000
0(
#155000
b1 U
b101101 a
b111111 0
b111111 b
b1111111 `
b1100000000 A
1(
#160000
0(
#165000
b101101 /
b101101 c
b1011011 a
b1100000 0
b1100000 b
b1111110 `
b10 U
b1100000000 A
1(
#170000
0(
#175000
b11 U
b1000000 /
b1000000 c
b110111 a
b1111100 `
b1100000000 A
1(
#180000
0(
#185000
b110111 /
b110111 c
b1101111 a
b1111000 `
b100 U
b1100000000 A
1(
#190000
0(
#195000
b101 U
b1000000 /
b1000000 c
b1011110 a
b1110000 `
b1100000000 A
1(
#200000
0(
#205000
b111101 a
b1100000 `
b110 U
b1100000000 A
1(
#210000
0(
#215000
b111 U
b111101 /
b111101 c
b1111011 a
b1000000 `
b1100000000 A
1(
#220000
0(
#225000
b1000000 /
b1000000 c
b1110110 a
b1000000 0
b1000000 b
b1 `
b1000 U
b1100000000 A
1(
#230000
0(
#235000
b1001 U
b1101100 a
b1 0
b1 b
b10 `
b1100000000 A
1(
#240000
0(
#245000
b1011000 a
b10 0
b10 b
b100 `
b1010 U
b1100000000 A
1(
#250000
0(
#255000
b1011 U
b110001 a
b100 0
b100 b
b1000 `
b1100000000 A
1(
#260000
0(
#265000
b110001 /
b110001 c
b1100011 a
b1000 0
b1000 b
b10000 `
b1100 U
b1100000000 A
1(
#270000
0(
#275000
b1101 U
b1000000 /
b1000000 c
b1000110 a
b10000 0
b10000 b
b100000 `
b1100000000 A
1(
#280000
0(
#285000
b1101 a
b100000 0
b100000 b
b1000001 `
b1110 U
b1100000000 A
1(
#290000
0(
#295000
b1111 U
b1101 /
b1101 c
b11010 a
b1000001 0
b1000001 b
b11 `
b1100000000 A
1(
#300000
0(
#305000
b11010 /
b11010 c
b110100 a
b11 0
b11 b
b110 `
b10000 U
b1100000000 A
1(
#310000
0(
#315000
b10001 U
b110100 /
b110100 c
b1101001 a
b110 0
b110 b
b1100 `
b1100000000 A
1(
#320000
0(
#325000
b1000000 /
b1000000 c
b1010010 a
b1100 0
b1100 b
b11000 `
b10010 U
b1100000000 A
1(
#330000
0(
#335000
b10011 U
b100101 a
b11000 0
b11000 b
b110000 `
b1100000000 A
1(
#340000
0(
#345000
b100101 /
b100101 c
b1001011 a
b110000 0
b110000 b
b1100001 `
b10100 U
b1100000000 A
1(
#350000
0(
#355000
b10101 U
b1000000 /
b1000000 c
b10111 a
b1100000 0
b1100000 b
b1000010 `
b1100000000 A
1(
#360000
0(
#365000
b10111 /
b10111 c
b101110 a
b1000010 0
b1000010 b
b101 `
b10110 U
b1100000000 A
1(
#370000
0(
#375000
b10111 U
b101110 /
b101110 c
b1011101 a
b101 0
b101 b
b1010 `
b1100000000 A
1(
#380000
0(
#385000
b1000000 /
b1000000 c
b111011 a
b1010 0
b1010 b
b10100 `
b11000 U
b1100000000 A
1(
#390000
0(
#395000
b11001 U
b111011 /
b111011 c
b1110111 a
b10100 0
b10100 b
b101000 `
b1100000000 A
1(
#400000
0(
#405000
b1000000 /
b1000000 c
b1101110 a
b101000 0
b101000 b
b1010001 `
b11010 U
b1100000000 A
1(
#410000
0(
#415000
b11011 U
b1011100 a
b1010001 0
b1010001 b
b100011 `
b1100000000 A
1(
#420000
0(
#425000
b111001 a
b100011 0
b100011 b
b1000111 `
b11100 U
b1100000000 A
1(
#430000
0(
#435000
b11101 U
b111001 /
b111001 c
b1110011 a
b1000111 0
b1000111 b
b1111 `
b1100000000 A
1(
#440000
0(
#445000
b1000000 /
b1000000 c
b1100110 a
b1111 0
b1111 b
b11110 `
b11110 U
b1100000000 A
1(
#450000
0(
#455000
b11111 U
b1001100 a
b11110 0
b11110 b
b111100 `
b1100000000 A
1(
#460000
0(
#465000
b11001 a
b111100 0
b111100 b
b1111001 `
b100000 U
b1100000000 A
1(
#470000
0(
#475000
b100001 U
b11001 /
b11001 c
b110010 a
b1100000 0
b1100000 b
b1110010 `
b1100000000 A
1(
#480000
0(
#485000
b110010 /
b110010 c
b1100101 a
b1100100 `
b100010 U
b1100000000 A
1(
#490000
0(
#495000
b100011 U
b1000000 /
b1000000 c
b1001010 a
b1001000 `
b1100000000 A
1(
#500000
0(
#505000
b10101 a
b1001000 0
b1001000 b
b10001 `
b100100 U
b1100000000 A
1(
#510000
0(
#515000
b100101 U
b10101 /
b10101 c
b101010 a
b10001 0
b10001 b
b100010 `
b1100000000 A
1(
#520000
0(
#525000
b101010 /
b101010 c
b1010101 a
b100010 0
b100010 b
b1000101 `
b100110 U
b1100000000 A
1(
#530000
0(
#535000
b100111 U
b1000000 /
b1000000 c
b101011 a
b1000101 0
b1000101 b
b1011 `
b1100000000 A
1(
#540000
0(
#545000
b101011 /
b101011 c
b1010111 a
b1011 0
b1011 b
b10110 `
b101000 U
b1100000000 A
1(
#550000
0(
#555000
b101001 U
b1000000 /
b1000000 c
b101111 a
b10110 0
b10110 b
b101100 `
b1100000000 A
1(
#560000
0(
#565000
b101111 /
b101111 c
b1011111 a
b101100 0
b101100 b
b1011001 `
b101010 U
b1100000000 A
1(
#570000
0(
#575000
b101011 U
b1000000 /
b1000000 c
b111111 a
b1011001 0
b1011001 b
b110011 `
b1100000000 A
1(
#580000
0(
#585000
b111111 /
b111111 c
b1111111 a
b110011 0
b110011 b
b1100111 `
b101100 U
b1100000000 A
1(
#590000
0(
#595000
b101101 U
b1000000 /
b1000000 c
b1111110 a
b1100000 0
b1100000 b
b1001110 `
b1100000000 A
1(
#600000
0(
#605000
b1111100 a
b1001110 0
b1001110 b
b11101 `
b101110 U
b1100000000 A
1(
#610000
0(
#615000
b101111 U
b1111000 a
b11101 0
b11101 b
b111010 `
b1100000000 A
1(
#620000
0(
